{
    "prodBuild": "true",
    "title": "Development | NIAID Design System",
    "cssPath": "../css/",
    "jsPath": "../js/",
    "imagePath": "../assets/",
    "navigationPrimaryActiveLink": "development",
    "jsIncludes": {
        "jquery": true,
        "select2": true,
        "materialize": true,
        "bootstrap": true,
        "matchMedia": true,
        "dataTables": true,
        "dateTimePicker": true
    },
    "links": {
        "index": "/",
        "design": "/design/",
        "development": "/development/",
        "components": "/components/",
        "themeBuilder": "/builder/",
        "getStarted": "/getting-started/",
        "migrationGuide": "/migration-guide/"
    },
    "columns": {
        "left": 3,
        "main": 7,
        "right": 2
    }
}